lightguide-0.4.0.dist-info/METADATA
lightguide-0.4.0.dist-info/WHEEL
lightguide-0.4.0.dist-info/license_files/LICENSE
lightguide/afk_filter_python.py
lightguide/io/__init__.py
lightguide/blast.py
lightguide/gf.py
lightguide/utils.py
lightguide/__init__.py
lightguide/filters.py
lightguide/signal.py
lightguide/client.py
lightguide/lightguide.pyi
lightguide/lightguide.pypy39-pp73-x86_64-linux-gnu.so
lightguide-0.4.0.dist-info/RECORD
