Metadata-Version: 2.1
Name: lightguide
Version: 0.4.0
Classifier: Programming Language :: Rust
Classifier: Programming Language :: Python :: Implementation :: CPython
Classifier: Programming Language :: Python :: Implementation :: PyPy
Requires-Dist: pyrocko>=2022.4.28
Requires-Dist: numpy>=1.20.0
Requires-Dist: requests>=2.20.0
Requires-Dist: myst-nb>=0.17.1; extra == 'docs'
Requires-Dist: semver>=3.0.0; extra == 'docs'
Requires-Dist: furo>=2023.3.27; extra == 'docs'
Requires-Dist: sphinx-copybutton>=0.5.1; extra == 'docs'
Requires-Dist: sphinx-design>=0.4.1; extra == 'docs'
Requires-Dist: ruff>=0.250; extra == 'dev'
Requires-Dist: black>=23.0.0; extra == 'dev'
Requires-Dist: isort; extra == 'dev'
Requires-Dist: pytest-benchmark; extra == 'dev'
Requires-Dist: pytest; extra == 'dev'
Provides-Extra: docs
Provides-Extra: dev
License-File: LICENSE
Summary: Tools for distributed acoustic sensing and modelling.
Keywords: distributed acoustic sensing,DAS,seismology,earthquake modelling
Author: Marius Paul Isken
Author-email: mi@gfz-potsdam.de
Requires-Python: >=3.8
Project-URL: Issues, https://github.com/pyrocko/lightguide/issues
Project-URL: Home, https://pyrocko.org
Project-URL: GitHub, https://github.com/pyrocko/lightguide
